<?xml version="1.0" encoding="utf-8"?>
<media>
	<media>
		<title>#CANLI - Cem Dizdar İle HT Spor Gündem</title>
		<thumb>https://i.ytimg.com/vi/rU75NxEv6lQ/hqdefault_live.jpg</thumb>
		<type>youtube</type>
		<src>rU75NxEv6lQ</src>
	</media>
	<media>
		<title>#CANLI - Cem Dizdar İle HT Spor Gündem</title>
		<thumb>https://i.ytimg.com/vi/RdpqsTbi_KU/hqdefault_live.jpg</thumb>
		<type>youtube</type>
		<src>RdpqsTbi_KU</src>
	</media>
	<media>
		<title>A Spor Canlı Yayın 🔴</title>
		<thumb>https://i.ytimg.com/vi/ysh-bPiD3Oo/hqdefault_live.jpg</thumb>
		<type>youtube</type>
		<src>ysh-bPiD3Oo</src>
	</media>
	<media>
		<title>SIFIR TV CANLI YAYIN</title>
		<thumb>https://i.ytimg.com/vi/JCSOAmBeXnY/hqdefault_live.jpg</thumb>
		<type>youtube</type>
		<src>JCSOAmBeXnY</src>
	</media>
	<media>
		<title>🔴 CANLI | Milliler zorlu virajda, üç büyüklerde son durum | Kontra Gazete</title>
		<thumb>https://i.ytimg.com/vi/7O2GgvOetiw/hqdefault_live.jpg</thumb>
		<type>youtube</type>
		<src>7O2GgvOetiw</src>
	</media>
	<media>
		<title>beIN SPORTS HABER Canlı Yayını | #beINSPORTS</title>
		<thumb>https://i.ytimg.com/vi/ovXYPBAzo-w/hqdefault_live.jpg</thumb>
		<type>youtube</type>
		<src>ovXYPBAzo-w</src>
	</media>
</media>